symbolang/__init__.py
symbolang/cli.py
symbolang/symbolang.py
symbolang-0.1.4.dist-info/METADATA
symbolang-0.1.4.dist-info/WHEEL
symbolang-0.1.4.dist-info/entry_points.txt
symbolang-0.1.4.dist-info/licenses/LICENSE
symbolang-0.1.4.dist-info/RECORD
