Metadata-Version: 2.4
Name: symbolang
Version: 0.1.4
Summary: A simple 2D programming language.
Author-email: thelegendofmario <ethanfrancis577@gmail.com>
License-File: LICENSE
Requires-Python: >=3.12
